django_better_admin_arrayfield/__init__.py
django_better_admin_arrayfield/apps.py
django_better_admin_arrayfield/admin/mixins.py
django_better_admin_arrayfield/forms/__init__.py
django_better_admin_arrayfield/forms/fields.py
django_better_admin_arrayfield/forms/widgets.py
django_better_admin_arrayfield/locale/es/LC_MESSAGES/django.po
django_better_admin_arrayfield/locale/fr/LC_MESSAGES/django.po
django_better_admin_arrayfield/locale/pt-br/LC_MESSAGES/django.po
django_better_admin_arrayfield/models/__init__.py
django_better_admin_arrayfield/models/fields.py
django_better_admin_arrayfield/static/css/django_better_admin_arrayfield.css
django_better_admin_arrayfield/static/css/django_better_admin_arrayfield.min.css
django_better_admin_arrayfield/static/js/django_better_admin_arrayfield.js
django_better_admin_arrayfield/static/js/django_better_admin_arrayfield.min.js
django_better_admin_arrayfield/templates/django_better_admin_arrayfield/forms/widgets/dynamic_array.html
django_better_admin_arrayfield-1.4.2.dist-info/AUTHORS.md
django_better_admin_arrayfield-1.4.2.dist-info/LICENSE
django_better_admin_arrayfield-1.4.2.dist-info/METADATA
django_better_admin_arrayfield-1.4.2.dist-info/WHEEL
django_better_admin_arrayfield-1.4.2.dist-info/top_level.txt
django_better_admin_arrayfield-1.4.2.dist-info/RECORD
