Metadata-Version: 2.1
Name: django-better-admin-arrayfield
Version: 1.4.2
Summary: Better ArrayField widget for admin
Home-page: https://github.com/gradam/django-better-admin-arrayfield
Author: Jakub Semik
Author-email: kuba.semik@gmail.com
License: MIT
Keywords: django-better-admin-arrayfield
Platform: UNKNOWN
Classifier: Development Status :: 4 - Beta
Classifier: Framework :: Django :: 3.1
Classifier: Framework :: Django :: 3.0
Classifier: Framework :: Django :: 2.2
Classifier: Framework :: Django :: 2.1
Classifier: Framework :: Django :: 2.0
Classifier: Intended Audience :: Developers
Classifier: License :: OSI Approved :: BSD License
Classifier: Natural Language :: English
Classifier: Programming Language :: Python :: 3
Classifier: Programming Language :: Python :: 3.5
Classifier: Programming Language :: Python :: 3.6
Classifier: Programming Language :: Python :: 3.7
Classifier: Programming Language :: Python :: 3.8
